rezero/__init__.py
rezero/transformer/__init__.py
rezero/transformer/rztx.py
rezero-0.1.0.dist-info/LICENSE
rezero-0.1.0.dist-info/METADATA
rezero-0.1.0.dist-info/WHEEL
rezero-0.1.0.dist-info/top_level.txt
rezero-0.1.0.dist-info/RECORD
