Metadata-Version: 2.1
Name: rezero
Version: 0.1.0
Summary: ReZero networks
Home-page: https://github.com/majumderb/rezero
Author: Thomas Bachlechner, Bodhisattwa Prasad Majumder, Huanru Henry Mao, Garrison W. Cottrell, Julian McAuley
Author-email: henry@calclavia.com
License: UNKNOWN
Platform: UNKNOWN
Classifier: Programming Language :: Python :: 3
Classifier: License :: OSI Approved :: MIT License
Classifier: Operating System :: OS Independent
Requires-Python: >=3.6
